playwright_har_tracer/__init__.py
playwright_har_tracer/constants.py
playwright_har_tracer/dataclasses/__init__.py
playwright_har_tracer/dataclasses/cdp.py
playwright_har_tracer/dataclasses/har.py
playwright_har_tracer/dataclasses/mixin.py
playwright_har_tracer/encoders.py
playwright_har_tracer/har_tracer.py
playwright_har_tracer/utils.py
playwright_har_tracer-0.3.2.dist-info/LICENSE
playwright_har_tracer-0.3.2.dist-info/WHEEL
playwright_har_tracer-0.3.2.dist-info/METADATA
playwright_har_tracer-0.3.2.dist-info/RECORD
