Metadata-Version: 2.1
Name: playwright-har-tracer
Version: 0.3.2
Summary: A Python implementation version of Playwright's HAR tracer
Home-page: https://github.com/ninoseki/playwright-har-tracer
Author: Manabu Niseki
Author-email: manabu.niseki@gmail.com
Requires-Python: >=3.8,<4.0
Classifier: Programming Language :: Python :: 3
Classifier: Programming Language :: Python :: 3.8
Classifier: Programming Language :: Python :: 3.9
Requires-Dist: dataclasses-json (>=0.5.6,<0.6.0)
Requires-Dist: python-dateutil (>=2.8.2,<3.0.0)
Project-URL: Repository, https://github.com/ninoseki/playwright-har-tracer
